{
    "10": {
        "runs": 10,
        "passes": 250,
        "comparisons": 278,
        "swaps": 224,
        "average passes": 25,
        "average comparisons": 27.8,
        "average swaps": 22.4
    },
    "20": {
        "runs": 10,
        "passes": 1000,
        "comparisons": 1125,
        "swaps": 969,
        "average passes": 100,
        "average comparisons": 112.5,
        "average swaps": 96.9
    },
    "30": {
        "runs": 10,
        "passes": 2250,
        "comparisons": 2522,
        "swaps": 2196,
        "average passes": 225,
        "average comparisons": 252.2,
        "average swaps": 219.6
    },
    "40": {
        "runs": 10,
        "passes": 4000,
        "comparisons": 4416,
        "swaps": 3750,
        "average passes": 400,
        "average comparisons": 441.6,
        "average swaps": 375
    },
    "50": {
        "runs": 10,
        "passes": 6250,
        "comparisons": 7118,
        "swaps": 6249,
        "average passes": 625,
        "average comparisons": 711.8,
        "average swaps": 624.9
    },
    "60": {
        "runs": 10,
        "passes": 9000,
        "comparisons": 10167,
        "swaps": 8941,
        "average passes": 900,
        "average comparisons": 1016.7,
        "average swaps": 894.1
    },
    "70": {
        "runs": 10,
        "passes": 12250,
        "comparisons": 13835,
        "swaps": 12271,
        "average passes": 1225,
        "average comparisons": 1383.5,
        "average swaps": 1227.1
    },
    "80": {
        "runs": 10,
        "passes": 16000,
        "comparisons": 17972,
        "swaps": 15714,
        "average passes": 1600,
        "average comparisons": 1797.2,
        "average swaps": 1571.4
    },
    "90": {
        "runs": 10,
        "passes": 20250,
        "comparisons": 22821,
        "swaps": 20075,
        "average passes": 2025,
        "average comparisons": 2282.1,
        "average swaps": 2007.5
    },
    "100": {
        "runs": 10,
        "passes": 25000,
        "comparisons": 28014,
        "swaps": 24479,
        "average passes": 2500,
        "average comparisons": 2801.4,
        "average swaps": 2447.9
    }
}